docs/COLLABORATE.md
docs/README.md
docs/refs.md
examples/cli.py
tests/__init__.py
tests/conftest.py
tests/test_factory.py
tests/test_names.py
tests/test_singleton.py
vacuna/__init__.py
vacuna/__version__.py
vacuna/lazy.py
vacuna-0.2.2.dist-info/LICENSE
vacuna-0.2.2.dist-info/WHEEL
vacuna-0.2.2.dist-info/METADATA
vacuna-0.2.2.dist-info/RECORD
